ansible_mkdocs/cache.py
ansible_mkdocs/gather.py
ansible_mkdocs/main.py
ansible_mkdocs/output.py
ansible_mkdocs/role.py
ansible_mkdocs/setup.py
ansible_mkdocs/types.py
ansible_mkdocs-0.0.2.dist-info/entry_points.txt
ansible_mkdocs-0.0.2.dist-info/WHEEL
ansible_mkdocs-0.0.2.dist-info/METADATA
ansible_mkdocs-0.0.2.dist-info/RECORD
