Metadata-Version: 2.1
Name: ansible-mkdocs
Version: 0.0.2
Summary: Auto-generate ansible role documentation
Home-page: https://github.com/tbobm/ansible-mkdocs
License: MIT
Keywords: ansible,documentation
Author: Theo "Bob" Massard
Author-email: tbobm@protonmail.com
Requires-Python: >=3.7,<4.0
Classifier: License :: OSI Approved :: MIT License
Classifier: Programming Language :: Python :: 3
Classifier: Programming Language :: Python :: 3.7
Classifier: Programming Language :: Python :: 3.8
Classifier: Programming Language :: Python :: 3.9
Requires-Dist: PyYAML (>=5.4.1,<6.0.0)
Requires-Dist: click (>=7.1.2,<8.0.0)
Project-URL: Repository, https://github.com/tbobm/ansible-mkdocs
